webspot/__init__.py
webspot/cmd/__init__.py
webspot/cmd/crawl.py
webspot/cmd/request.py
webspot/cmd/web.py
webspot/constants/__init__.py
webspot/constants/detector.py
webspot/constants/field_extract_rule_type.py
webspot/constants/html_request_method.py
webspot/constants/request_status.py
webspot/crawler/__init__.py
webspot/crawler/actions/__init__.py
webspot/crawler/actions/run_crawler.py
webspot/crawler/crawler/__init__.py
webspot/crawler/crawler/items.py
webspot/crawler/crawler/middlewares.py
webspot/crawler/crawler/pipelines.py
webspot/crawler/crawler/settings.py
webspot/crawler/crawler/spiders/__init__.py
webspot/crawler/crawler/spiders/web_spider.py
webspot/db/__init__.py
webspot/db/connect.py
webspot/detect/__init__.py
webspot/detect/detectors/__init__.py
webspot/detect/detectors/base.py
webspot/detect/detectors/pagination.py
webspot/detect/detectors/plain_list.py
webspot/detect/detectors/plain_table.py
webspot/detect/models/__init__.py
webspot/detect/models/list_result.py
webspot/detect/models/result.py
webspot/detect/models/selector.py
webspot/detect/models/stats.py
webspot/detect/models/table_result.py
webspot/detect/utils/__init__.py
webspot/detect/utils/highlight_html.py
webspot/detect/utils/math.py
webspot/detect/utils/transform_html_links.py
webspot/detect/utils/url.py
webspot/extract/__init__.py
webspot/extract/extract_results.py
webspot/graph/__init__.py
webspot/graph/graph_loader.py
webspot/graph/models/__init__.py
webspot/graph/models/node.py
webspot/logging/__init__.py
webspot/models/__init__.py
webspot/models/base.py
webspot/models/node.py
webspot/models/request.py
webspot/models/user.py
webspot/request/__init__.py
webspot/request/html_requester.py
webspot/test/__init__.py
webspot/test/crawler/__init__.py
webspot/test/crawler/test_crawler.py
webspot/test/detect/__init__.py
webspot/test/detect/test_plain_list.py
webspot/test/logging/__init__.py
webspot/test/logging/test_get_logger.py
webspot/test/web/__init__.py
webspot/test/web/routes/__init__.py
webspot-0.1.4.dist-info/LICENSE
webspot-0.1.4.dist-info/METADATA
webspot-0.1.4.dist-info/WHEEL
webspot-0.1.4.dist-info/entry_points.txt
webspot-0.1.4.dist-info/top_level.txt
webspot-0.1.4.dist-info/RECORD
