Metadata-Version: 2.1
Name: webspot
Version: 0.1.4
Summary: An intelligent web service to automatically detect web content and extract information from it.
Home-page: https://github.com/tikazyq/webspot
Author: tikazyq
Author-email: tikazyq@163.com
License: BSD-3-Clause
Classifier: Programming Language :: Python :: 3
Classifier: License :: OSI Approved :: BSD License
Classifier: Operating System :: OS Independent
License-File: LICENSE
Requires-Dist: scrapy (==2.7.1)
Requires-Dist: html-to-json-enhanced (>=1.0.5)
Requires-Dist: pandas (==1.5.3)
Requires-Dist: scikit-learn (==1.2.0)
Requires-Dist: fastapi (==0.89.1)
Requires-Dist: Jinja2 (==3.1.2)
Requires-Dist: uvicorn (==0.20.0)
Requires-Dist: SQLAlchemy (==2.0.2)
Requires-Dist: PyMySQL (==1.0.2)
Requires-Dist: alembic (==1.9.3)
Requires-Dist: python-dotenv (==0.21.1)
Requires-Dist: mongoengine (==0.26.0)
Requires-Dist: pytest (==7.2.1)
Requires-Dist: pytest-async (==0.1.1)
Requires-Dist: retrying (==1.3.4)
Requires-Dist: httpx (==0.23.3)
Requires-Dist: cssutils (==2.6.0)
Requires-Dist: autopager (==0.3.1)
